funcat/VERSION.txt
funcat/__init__.py
funcat/account.py
funcat/api.py
funcat/context.py
funcat/func.py
funcat/helper.py
funcat/indicators.py
funcat/time_series.py
funcat/utils.py
funcat/data/__init__.py
funcat/data/akshare_backend.py
funcat/data/akshare_hk_backend.py
funcat/data/akshare_us_backend.py
funcat/data/backend.py
funcat/data/crypto_backend.py
funcat/data/order_book_id_list.csv
funcat/data/order_book_id_list_us.csv
funcat/data/rqalpha_data_backend.py
funcat/data/rqdata_data_backend.py
funcat/data/rt_data.py
funcat/data/rt_data_from_tencent.py
funcat/data/stock_basic.csv
funcat/data/tencent_backend.py
funcat/data/tushare_backend.py
funcat/data/okex/__init__.py
funcat/data/okex/account_api.py
funcat/data/okex/client.py
funcat/data/okex/consts.py
funcat/data/okex/ett_api.py
funcat/data/okex/exceptions.py
funcat/data/okex/futures_api.py
funcat/data/okex/lever_api.py
funcat/data/okex/spot_api.py
funcat/data/okex/swap_api.py
funcat/data/okex/utils.py
funcat/data/okex/websocket.py
funcat3-1.1.8.dist-info/LICENSE
funcat3-1.1.8.dist-info/METADATA
funcat3-1.1.8.dist-info/WHEEL
funcat3-1.1.8.dist-info/top_level.txt
funcat3-1.1.8.dist-info/RECORD
