Metadata-Version: 2.1
Name: funcat3
Version: 1.1.8
Home-page: https://github.com/mapicccy/funcat
Author: Guanjun
Author-email: mapicccy@gmail.com
License: Apache License v2
Classifier: Programming Language :: Python
Classifier: Operating System :: Microsoft :: Windows
Classifier: Operating System :: Unix
Classifier: Programming Language :: Python :: 2.7
Classifier: Programming Language :: Python :: 3.4
Classifier: Programming Language :: Python :: 3.5
Classifier: Programming Language :: Python :: 3.6
Classifier: Programming Language :: Python :: 3.7
Classifier: Programming Language :: Python :: 3.8
Classifier: Programming Language :: Python :: 3.9
Classifier: Programming Language :: Python :: 3.10
Classifier: Programming Language :: Python :: 3.11
License-File: LICENSE
Requires-Dist: setuptools
Requires-Dist: wheel
Requires-Dist: numpy
Requires-Dist: six
Requires-Dist: backports.functools_lru_cache
Requires-Dist: pandas==1.5.3
Requires-Dist: lxml
Requires-Dist: requests
Requires-Dist: cached-property
Requires-Dist: tqdm
Requires-Dist: python-dateutil
Requires-Dist: pytz
Requires-Dist: idna
Requires-Dist: certifi
Requires-Dist: soupsieve
Requires-Dist: websocket-client
Requires-Dist: charset_normalizer
Requires-Dist: tushare
Requires-Dist: akshare
